[
  {
    "file": "backracks:itemtypes/backrack-copper.json",
    "op": "replace",
    "path": "/attributes/backpackByType/*-normal/quantitySlots",
    "value": 1,
    "dependsOn": [
      {
        "modid": "primitivebackpacks"
      }
    ]
  },
  {
    "file": "backracks:itemtypes/backrack-tinbronze.json",
    "op": "replace",
    "path": "/attributes/backpackByType/*-normal/quantitySlots",
    "value": 1,
    "dependsOn": [
      {
        "modid": "primitivebackpacks"
      }
    ]
  },
  {
    "file": "backracks:itemtypes/basketbackrack-normal.json",
    "op": "replace",
    "path": "/attributes/backpackByType/*-normal/quantitySlots",
    "value": 14,
    "dependsOn": [
      {
        "modid": "primitivebackpacks"
      }
    ]
  },
  {
    "file": "backracks:itemtypes/basketbackrackhunter-normal.json",
    "op": "replace",
    "path": "/attributes/backpackByType/*-normal/quantitySlots",
    "value": 24,
    "dependsOn": [
      {
        "modid": "primitivebackpacks"
      }
    ]
  },
  {
    "file": "backracks:itemtypes/claybackrack-normal.json",
    "op": "replace",
    "path": "/attributes/backpackByType/*-normal/quantitySlots",
    "value": 24,
    "dependsOn": [
      {
        "modid": "primitivebackpacks"
      }
    ]
  },
  {
    "file": "backracks:itemtypes/foragerbackrack-normal.json",
    "op": "replace",
    "path": "/attributes/backpackByType/*-normal/quantitySlots",
    "value": 24,
    "dependsOn": [
      {
        "modid": "primitivebackpacks"
      }
    ]
  },
  {
    "file": "backracks:itemtypes/shelfbackrack-normal.json",
    "op": "replace",
    "path": "/attributes/backpackByType/*-normal/quantitySlots",
    "value": 14,
    "dependsOn": [
      {
        "modid": "primitivebackpacks"
      }
    ]
  },
  {
    "file": "backracks:itemtypes/firewoodbackrack-normal.json",
    "op": "replace",
    "path": "/attributes/backpackByType/*-normal/quantitySlots",
    "value": 24,
    "dependsOn": [
      {
        "modid": "primitivebackpacks"
      }
    ]
  },
  {
    "file": "backracks:itemtypes/logbackrack-normal.json",
    "op": "replace",
    "path": "/attributes/backpackByType/*-normal/quantitySlots",
    "value": 24,
    "dependsOn": [
      {
        "modid": "primitivebackpacks"
      }
    ]
  },
  {
    "file": "backracks:itemtypes/cratebackrack-copper.json",
    "op": "replace",
    "path": "/attributes/backpackByType/*-normal/quantitySlots",
    "value": 30,
    "dependsOn": [
      {
        "modid": "primitivebackpacks"
      }
    ]
  },
  {
    "file": "backracks:itemtypes/chestbackrack-copper.json",
    "op": "replace",
    "path": "/attributes/backpackByType/*-normal/quantitySlots",
    "value": 16,
    "dependsOn": [
      {
        "modid": "primitivebackpacks"
      }
    ]
  }
]